Examples/__init__.py
Miscblox/__init__.py
Miscblox/miscblox.py
Miscblox/Classes/__init__.py
Miscblox/Classes/account.py
Miscblox/Classes/Account/Information.py
Miscblox/Classes/Account/Settings.py
Miscblox/Classes/Account/__init__.py
Miscblox/Classes/Account/campaigns.py
Miscblox/Datamodels/__init__.py
Miscblox/Datamodels/http.py
Miscblox/Datamodels/roblox.py
Miscblox/Functions/__init__.py
Miscblox/Functions/logger.py
Miscblox-1.0.0.dist-info/METADATA
Miscblox-1.0.0.dist-info/WHEEL
Miscblox-1.0.0.dist-info/top_level.txt
Miscblox-1.0.0.dist-info/RECORD
