Metadata-Version: 2.1
Name: Miscblox
Version: 1.0.0
Summary: An API wrapper for the Roblox that supports endpoints that other API wrappers don't.
Author: mark.api
Classifier: Programming Language :: Python :: 3
Classifier: License :: OSI Approved :: MIT License
Classifier: Operating System :: OS Independent
Requires-Python: >=3.6
Requires-Dist: httpx
Requires-Dist: asyncio
